License.txt
MANIFEST.in
Readme.md
setup.py
psd2pngs/__init__.py
psd2pngs/__main__.py
psd2pngs/convertion.py
psd2pngs/layer_info.py
psd2pngs/layer_save.py
psd2pngs/safe_name.py
psd2pngs/unpack.py
psd2pngs/version.py
psd2pngs.egg-info/PKG-INFO
psd2pngs.egg-info/SOURCES.txt
psd2pngs.egg-info/dependency_links.txt
psd2pngs.egg-info/entry_points.txt
psd2pngs.egg-info/requires.txt
psd2pngs.egg-info/top_level.txt
tests/__init__.py
tests/test_convert.py
tests/test_multiprocessing.py