Metadata-Version: 2.1
Name: psd2pngs
Version: 1.2.4
Summary: Convert a PSD file to PNG files while maintaining the layer hierarchy.
Home-page: https://github.com/34j/psd2pngs
Author: 34j
License: MIT
Project-URL: Documentation, https://psd2pngs.readthedocs.io/
Project-URL: Github, https://github.com/34j/psd2pngs
Keywords: psd
Classifier: Programming Language :: Python :: 3.9
Classifier: Programming Language :: Python :: 3.10
Classifier: Programming Language :: Python :: 3.11
Classifier: Programming Language :: Python :: 3.12
Classifier: License :: OSI Approved :: MIT License
Classifier: Operating System :: OS Independent
Classifier: Natural Language :: English
Classifier: Topic :: Multimedia :: Graphics :: Graphics Conversion
Classifier: Intended Audience :: End Users/Desktop
Requires-Python: >=3.9
License-File: License.txt
